crescent/__init__.py
crescent/core/__init__.py
crescent/core/constants.py
crescent/core/exceptions.py
crescent/core/mapping.py
crescent/core/model.py
crescent/core/parameter.py
crescent/core/resource.py
crescent/core/resource_attrs.py
crescent/core/tag.py
crescent/core/template.py
crescent/core/type.py
crescent/core/validator.py
crescent/resources/__init__.py
crescent/resources/ecr/__init__.py
crescent/resources/ecr/lifecycle_policy.py
crescent/resources/ecr/repository.py
crescent/resources/efs/__init__.py
crescent/resources/efs/file_system/__init__.py
crescent/resources/efs/file_system/constants.py
crescent/resources/efs/file_system/efs_tag.py
crescent/resources/efs/file_system/file_system.py
crescent/resources/efs/file_system/lifecycle_policy.py
crescent/resources/efs/mount_target/__init__.py
crescent/resources/efs/mount_target/mount_target.py
crescent/resources/firehose/__init__.py
crescent/resources/firehose/buffering_hints.py
crescent/resources/firehose/cloudwatch_logging_options.py
crescent/resources/firehose/constants.py
crescent/resources/firehose/copy_command.py
crescent/resources/firehose/data_format_conversion_configuration.py
crescent/resources/firehose/delivery_stream.py
crescent/resources/firehose/deserializer.py
crescent/resources/firehose/elasticsearch_buffering_hints.py
crescent/resources/firehose/elasticsearch_destination_configuration.py
crescent/resources/firehose/elasticsearch_retry_options.py
crescent/resources/firehose/encryption_configuration.py
crescent/resources/firehose/extended_s3_destination_configuration.py
crescent/resources/firehose/hive_json_ser_de.py
crescent/resources/firehose/input_format_configuration.py
crescent/resources/firehose/kinesis_stream_source_configuration.py
crescent/resources/firehose/kms_encryption_config.py
crescent/resources/firehose/lambda_processor.py
crescent/resources/firehose/openx_json_ser_de.py
crescent/resources/firehose/orc_ser_de.py
crescent/resources/firehose/output_format_configuration.py
crescent-0.0.17.dist-info/LICENSE
crescent-0.0.17.dist-info/METADATA
crescent-0.0.17.dist-info/WHEEL
crescent-0.0.17.dist-info/top_level.txt
crescent-0.0.17.dist-info/RECORD
