Metadata-Version: 2.1
Name: crescent
Version: 0.0.17
Summary: Crescent is CloudFormation template generator that validates your template and inform you easily.
Home-page: https://github.com/mpolatcan/crescent
Author: Mutlu Polatcan
Author-email: mutlupolatcan@gmail.com
License: UNKNOWN
Platform: UNKNOWN
Classifier: Programming Language :: Python :: 3.6
Classifier: License :: OSI Approved :: Apache Software License
Classifier: Operating System :: OS Independent
Requires-Dist: PyYAML
